netbox_certificate-1.0.1.dist-info/licenses/LICENSE
netbox_certificate_management/__init__.py
netbox_certificate_management/apps.py
netbox_certificate_management/jobs.py
netbox_certificate_management/navigation.py
netbox_certificate_management/urls.py
netbox_certificate_management/api/__init__.py
netbox_certificate_management/api/urls.py
netbox_certificate_management/api/views.py
netbox_certificate_management/api/serializers/__init__.py
netbox_certificate_management/api/serializers/certificate_serializers.py
netbox_certificate_management/filtersets/__init__.py
netbox_certificate_management/filtersets/certificate.py
netbox_certificate_management/forms/__init__.py
netbox_certificate_management/forms/certificate.py
netbox_certificate_management/migrations/0001_initial.py
netbox_certificate_management/migrations/__init__.py
netbox_certificate_management/models/__init__.py
netbox_certificate_management/models/certificate.py
netbox_certificate_management/tables/__init__.py
netbox_certificate_management/tables/certificate.py
netbox_certificate_management/templates/netbox_certificate_management/application.html
netbox_certificate_management/templates/netbox_certificate_management/assign_application.html
netbox_certificate_management/templates/netbox_certificate_management/assign_cluster.html
netbox_certificate_management/templates/netbox_certificate_management/assign_cluster_group.html
netbox_certificate_management/templates/netbox_certificate_management/assign_contact.html
netbox_certificate_management/templates/netbox_certificate_management/assign_device.html
netbox_certificate_management/templates/netbox_certificate_management/assign_virtual_machine.html
netbox_certificate_management/templates/netbox_certificate_management/cert_import.html
netbox_certificate_management/templates/netbox_certificate_management/certificate.html
netbox_certificate_management/templates/netbox_certificate_management/certificate_application.html
netbox_certificate_management/templates/netbox_certificate_management/certificate_cluster.html
netbox_certificate-1.0.1.dist-info/METADATA
netbox_certificate-1.0.1.dist-info/WHEEL
netbox_certificate-1.0.1.dist-info/top_level.txt
netbox_certificate-1.0.1.dist-info/RECORD
