Metadata-Version: 2.4
Name: netbox-certificate
Version: 1.0.1
Summary: ADESTIS Certificate Management
Home-page: https://github.com/an-adestis/ADESTIS-Netbox-Certificate-Management
Author: ADESTIS GmbH
Author-email: pypi@adestis.de
License: GPL-3.0-only
Keywords: netbox,netbox-plugin,plugin
License-File: LICENSE
Dynamic: author
Dynamic: author-email
Dynamic: description
Dynamic: description-content-type
Dynamic: home-page
Dynamic: keywords
Dynamic: license
Dynamic: license-file
Dynamic: summary
